textfilter/__init__.py
textfilter/__main__.py
textfilter/textfilter.py
textfilter-0.1.0.dist-info/AUTHORS.rst
textfilter-0.1.0.dist-info/LICENSE
textfilter-0.1.0.dist-info/METADATA
textfilter-0.1.0.dist-info/WHEEL
textfilter-0.1.0.dist-info/entry_points.txt
textfilter-0.1.0.dist-info/top_level.txt
textfilter-0.1.0.dist-info/RECORD
